{"instagram.com":{"/":{"rur":{"key":"rur","value":"FRC","domain":"instagram.com","path":"/","secure":true,"httpOnly":true,"hostOnly":false,"creation":"2019-06-03T05:52:54.676Z","lastAccessed":"2019-06-04T13:37:54.575Z"},"mid":{"key":"mid","value":"XPS1tAABAAHEwuw_uIRxM2kklaSL","expires":"2029-05-31T05:52:52.000Z","maxAge":315360000,"domain":"instagram.com","path":"/","secure":true,"hostOnly":false,"creation":"2019-06-03T05:52:54.686Z","lastAccessed":"2019-06-04T13:37:50.039Z"},"csrftoken":{"key":"csrftoken","value":"4lvljUMKn2R7QJIjTVwm6MKhQbJ09690","expires":"2020-06-02T13:37:53.000Z","maxAge":31449600,"domain":"instagram.com","path":"/","secure":true,"hostOnly":false,"creation":"2019-06-03T05:52:54.692Z","lastAccessed":"2019-06-04T13:37:54.578Z"},"ds_user":{"key":"ds_user","value":"gamer.wraps","expires":"2019-09-01T05:52:53.000Z","maxAge":7776000,"domain":"instagram.com","path":"/","secure":true,"httpOnly":true,"hostOnly":false,"creation":"2019-06-03T05:52:56.026Z","lastAccessed":"2019-06-04T13:37:50.039Z"},"shbid":{"key":"shbid","value":"18232","expires":"2019-06-10T05:52:53.000Z","maxAge":604800,"domain":"instagram.com","path":"/","secure":true,"httpOnly":true,"hostOnly":false,"creation":"2019-06-03T05:52:56.027Z","lastAccessed":"2019-06-04T13:37:50.039Z"},"shbts":{"key":"shbts","value":"1559541173.9202266","expires":"2019-06-10T05:52:53.000Z","maxAge":604800,"domain":"instagram.com","path":"/","secure":true,"httpOnly":true,"hostOnly":false,"creation":"2019-06-03T05:52:56.028Z","lastAccessed":"2019-06-04T13:37:50.039Z"},"ds_user_id":{"key":"ds_user_id","value":"2272889933","expires":"2019-09-02T13:37:53.000Z","maxAge":7776000,"domain":"instagram.com","path":"/","secure":true,"hostOnly":false,"creation":"2019-06-03T05:52:56.029Z","lastAccessed":"2019-06-04T13:37:54.576Z"},"urlgen":{"key":"urlgen","value":"\"{\\\"209.209.231.102\\\": 63008\\054 \\\"104.151.6.52\\\": 18978}:1hY9dR:Z4BZKEpZ2k-cXg47sRYXGw_q4oI\"","domain":"instagram.com","path":"/","secure":true,"httpOnly":true,"hostOnly":false,"creation":"2019-06-03T05:52:56.030Z","lastAccessed":"2019-06-04T13:37:54.577Z"},"sessionid":{"key":"sessionid","value":"2272889933%3AOdrDMbXHChREP9%3A5","expires":"2020-06-03T13:08:25.000Z","maxAge":31536000,"domain":"instagram.com","path":"/","secure":true,"httpOnly":true,"hostOnly":false,"creation":"2019-06-03T05:52:56.031Z","lastAccessed":"2019-06-04T13:37:50.039Z"},"is_starred_enabled":{"key":"is_starred_enabled","value":"yes","expires":"2029-05-31T05:52:55.000Z","maxAge":315360000,"domain":"instagram.com","path":"/","secure":true,"httpOnly":true,"hostOnly":false,"creation":"2019-06-03T05:52:57.884Z","lastAccessed":"2019-06-04T13:37:50.039Z"}}}}